streamlit_flowsheet/__init__.py
streamlit_flowsheet/frontend/build/index.css
streamlit_flowsheet/frontend/build/index.html
streamlit_flowsheet/frontend/build/index.js
streamlit_flowsheet-0.2.11.dist-info/licenses/LICENSE
streamlit_flowsheet-0.2.11.dist-info/METADATA
streamlit_flowsheet-0.2.11.dist-info/WHEEL
streamlit_flowsheet-0.2.11.dist-info/top_level.txt
streamlit_flowsheet-0.2.11.dist-info/RECORD
