Metadata-Version: 2.4
Name: streamlit-flowsheet
Version: 0.2.11
Summary: A Streamlit component for rendering process flowsheet diagrams with interactive selection
Author-email: Everton Colling <evertoncolling@gmail.com>
License-Expression: MIT
Project-URL: Homepage, https://github.com/evertoncolling/streamlit-flowsheet
Project-URL: Repository, https://github.com/evertoncolling/streamlit-flowsheet
Project-URL: Issues, https://github.com/evertoncolling/streamlit-flowsheet/issues
Keywords: streamlit,flowsheet,diagram,visualization,component
Classifier: Development Status :: 3 - Alpha
Classifier: Intended Audience :: Developers
Classifier: Programming Language :: Python :: 3
Classifier: Programming Language :: Python :: 3.9
Classifier: Programming Language :: Python :: 3.10
Classifier: Programming Language :: Python :: 3.11
Classifier: Programming Language :: Python :: 3.12
Classifier: Topic :: Software Development :: Libraries :: Python Modules
Requires-Python: >=3.9
License-File: LICENSE
Requires-Dist: streamlit>=1.28.0
Dynamic: license-file
